<?xml version="1.0" encoding="UTF-8" standalone="yes"?><response><appID>247080</appID><appFriendlyName>247080</appFriendlyName><leaderboardID>2047674</leaderboardID><totalLeaderboardEntries>218</totalLeaderboardEntries><entryStart>1</entryStart><entryEnd>218</entryEnd><resultCount>218</resultCount><entries><entry><steamid>76561198041011456</steamid><score>99784884</score><rank>1</rank><ugcid>845970674187316295</ugcid><details>0500000006000000</details></entry><entry><steamid>76561197998799529</steamid><score>99772982</score><rank>2</rank><ugcid>850473600829582725</ugcid><details>0500000006000000</details></entry><entry><steamid>76561198000263514</steamid><score>99725114</score><rank>3</rank><ugcid>859481242273348890</ugcid><details>0500000006000000</details></entry><entry><steamid>76561198118733148</steamid><score>99721514</score><rank>4</rank><ugcid>844844771622940147</ugcid><details>0500000006000000</details></entry><entry><steamid>76561197984187817</steamid><score>99714840</score><rank>5</rank><ugcid>854977642905971851</ugcid><details>0500000006000000</details></entry><entry><steamid>76561198136201511</steamid><score>99703704</score><rank>6</rank><ugcid>867362542180785834</ugcid><details>0500000006000000</details></entry><entry><steamid>76561197998362244</steamid><score>99700566</score><rank>7</rank><ugcid>849348382428390127</ugcid><details>0500000006000000</details></entry><entry><steamid>76561198112122029</steamid><score>99698180</score><rank>8</rank><ugcid>854973983188528047</ugcid><details>0500000006000000</details></entry><entry><steamid>76561198054470568</steamid><score>99693972</score><rank>9</rank><ugcid>847095572536110834</ugcid><details>0500000006000000</details></entry><entry><steamid>76561197975956199</steamid><score>99692443</score><rank>10</rank><ugcid>878622169388232548</ugcid><details>0500000006000000</details></entry><entry><steamid>76561197993247154</steamid><score>99686441</score><rank>11</rank><ugcid>863986341952537584</ugcid><details>0500000006000000</details></entry><entry><steamid>76561198031063446</steamid><score>99669359</score><rank>12</rank><ugcid>861729956027275884</ugcid><details>0500000006000000</details></entry><entry><steamid>76561198039684185</steamid><score>99650529</score><rank>13</rank><ugcid>852725750660478028</ugcid><details>0500000006000000</details></entry><entry><steamid>76561198089956676</steamid><score>99634651</score><rank>14</rank><ugcid>847096251123965224</ugcid><details>0500000006000000</details></entry><entry><steamid>76561197996690770</steamid><score>99628403</score><rank>15</rank><ugcid>868489312389356243</ugcid><details>0500000006000000</details></entry><entry><steamid>76561198028008855</steamid><score>99612392</score><rank>16</rank><ugcid>850469194753481095</ugcid><details>0500000006000000</details></entry><entry><steamid>76561198055098680</steamid><score>99604143</score><rank>17</rank><ugcid>861734217654203284</ugcid><details>0500000006000000</details></entry><entry><steamid>76561197973971839</steamid><score>99597097</score><rank>18</rank><ugcid>869614342757083616</ugcid><details>0500000006000000</details></entry><entry><steamid>76561198058867434</steamid><score>99590959</score><rank>19</rank><ugcid>870740868156942464</ugcid><details>0500000006000000</details></entry><entry><steamid>76561198002854407</steamid><score>99587505</score><rank>20</rank><ugcid>863982936801966123</ugcid><details>0500000006000000</details></entry><entry><steamid>76561198010192987</steamid><score>99586323</score><rank>21</rank><ugcid>865107698018579014</ugcid><details>0500000006000000</details></entry><entry><steamid>76561198195540037</steamid><score>99585969</score><rank>22</rank><ugcid>850471480289979025</ugcid><details>0500000006000000</details></entry><entry><steamid>76561198041259046</steamid><score>99578222</score><rank>23</rank><ugcid>860607050009025222</ugcid><details>0500000006000000</details></entry><entry><steamid>76561198168248850</steamid><score>99576188</score><rank>24</rank><ugcid>858353982355788559</ugcid><details>0500000006000000</details></entry><entry><steamid>76561198136926537</steamid><score>99575019</score><rank>25</rank><ugcid>849344744319100243</ugcid><details>0500000006000000</details></entry><entry><steamid>76561198072593083</steamid><score>99571341</score><rank>26</rank><ugcid>865109554285087478</ugcid><details>0500000006000000</details></entry><entry><steamid>76561198109414601</steamid><score>99568622</score><rank>27</rank><ugcid>851598038667617266</ugcid><details>0500000006000000</details></entry><entry><steamid>76561198034369998</steamid><score>99564171</score><rank>28</rank><ugcid>862858943316624445</ugcid><details>0500000006000000</details></entry><entry><steamid>76561198046471496</steamid><score>99563414</score><rank>29</rank><ugcid>843718551399896820</ugcid><details>0500000006000000</details></entry><entry><steamid>76561197965084592</steamid><score>99561806</score><rank>30</rank><ugcid>842589465340108359</ugcid><details>0500000006000000</details></entry><entry><steamid>76561198028146044</steamid><score>99558848</score><rank>31</rank><ugcid>847096738987356125</ugcid><details>0500000006000000</details></entry><entry><steamid>76561198194866686</steamid><score>99555580</score><rank>32</rank><ugcid>862859183142474339</ugcid><details>0500000006000000</details></entry><entry><steamid>76561198044886811</steamid><score>99554682</score><rank>33</rank><ugcid>866236641742498891</ugcid><details>0500000006000000</details></entry><entry><steamid>76561197995770129</steamid><score>99552992</score><rank>34</rank><ugcid>850474043001668181</ugcid><details>0500000006000000</details></entry><entry><steamid>76561197991823888</steamid><score>99552160</score><rank>35</rank><ugcid>844841193623391636</ugcid><details>0500000006000000</details></entry><entry><steamid>76561197987716503</steamid><score>99550933</score><rank>36</rank><ugcid>865110742928041853</ugcid><details>0500000006000000</details></entry><entry><steamid>76561197996696153</steamid><score>99547780</score><rank>37</rank><ugcid>852725391218012451</ugcid><details>0500000006000000</details></entry><entry><steamid>76561198030783149</steamid><score>99543282</score><rank>38</rank><ugcid>856103543882625222</ugcid><details>0500000006000000</details></entry><entry><steamid>76561198034909460</steamid><score>99542284</score><rank>39</rank><ugcid>847096466141200101</ugcid><details>0500000006000000</details></entry><entry><steamid>76561197994523755</steamid><score>99539471</score><rank>40</rank><ugcid>867361404259992496</ugcid><details>0500000006000000</details></entry><entry><steamid>76561198052453103</steamid><score>99539095</score><rank>41</rank><ugcid>867362542181220587</ugcid><details>0500000006000000</details></entry><entry><steamid>76561198092135783</steamid><score>99534249</score><rank>42</rank><ugcid>876377203257845241</ugcid><details>0500000006000000</details></entry><entry><steamid>76561198002124175</steamid><score>99531937</score><rank>43</rank><ugcid>854973547812207585</ugcid><details>0500000006000000</details></entry><entry><steamid>76561198033762881</steamid><score>99529746</score><rank>44</rank><ugcid>851597253397422235</ugcid><details>0500000006000000</details></entry><entry><steamid>76561198089674311</steamid><score>99529446</score><rank>45</rank><ugcid>865110742928042555</ugcid><details>0500000006000000</details></entry><entry><steamid>76561198078999800</steamid><score>99522605</score><rank>46</rank><ugcid>842591904150405420</ugcid><details>0500000006000000</details></entry><entry><steamid>76561197989223079</steamid><score>99519182</score><rank>47</rank><ugcid>865110015597598132</ugcid><details>0500000006000000</details></entry><entry><steamid>76561198004612980</steamid><score>99511992</score><rank>48</rank><ugcid>856104172567412456</ugcid><details>0500000006000000</details></entry><entry><steamid>76561198010626924</steamid><score>99498688</score><rank>49</rank><ugcid>857235318923396659</ugcid><details>0500000006000000</details></entry><entry><steamid>76561197968400814</steamid><score>99497949</score><rank>50</rank><ugcid>861729391591162329</ugcid><details>0500000006000000</details></entry><entry><steamid>76561198096014598</steamid><score>99495454</score><rank>51</rank><ugcid>886504015610153634</ugcid><details>0500000006000000</details></entry><entry><steamid>76561198159114908</steamid><score>99494750</score><rank>52</rank><ugcid>858356106746023580</ugcid><details>0500000006000000</details></entry><entry><steamid>76561198006939846</steamid><score>99493774</score><rank>53</rank><ugcid>874118482746784239</ugcid><details>0500000006000000</details></entry><entry><steamid>76561198040828497</steamid><score>99487927</score><rank>54</rank><ugcid>851605540496731897</ugcid><details>0500000006000000</details></entry><entry><steamid>76561198144979533</steamid><score>99487832</score><rank>55</rank><ugcid>852723469542757321</ugcid><details>0500000006000000</details></entry><entry><steamid>76561198044519872</steamid><score>99487173</score><rank>56</rank><ugcid>845970274589589706</ugcid><details>0500000006000000</details></entry><entry><steamid>76561198070948070</steamid><score>99487074</score><rank>57</rank><ugcid>857233790544731133</ugcid><details>0500000006000000</details></entry><entry><steamid>76561198165653450</steamid><score>99486945</score><rank>58</rank><ugcid>872992582832024414</ugcid><details>0500000006000000</details></entry><entry><steamid>76561198070356870</steamid><score>99486613</score><rank>59</rank><ugcid>884258438258828801</ugcid><details>0500000006000000</details></entry><entry><steamid>76561198149556207</steamid><score>99485611</score><rank>60</rank><ugcid>863991188859408687</ugcid><details>0500000006000000</details></entry><entry><steamid>76561197967734490</steamid><score>99484419</score><rank>61</rank><ugcid>858353438108799771</ugcid><details>0500000006000000</details></entry><entry><steamid>76561198098788416</steamid><score>99481393</score><rank>62</rank><ugcid>847094133790674080</ugcid><details>0500000006000000</details></entry><entry><steamid>76561197969170907</steamid><score>99479335</score><rank>63</rank><ugcid>862856504897756444</ugcid><details>0500000006000000</details></entry><entry><steamid>76561198025286155</steamid><score>99478980</score><rank>64</rank><ugcid>866236237116088313</ugcid><details>0500000006000000</details></entry><entry><steamid>76561198093336562</steamid><score>99478601</score><rank>65</rank><ugcid>856101166819531365</ugcid><details>0500000006000000</details></entry><entry><steamid>76561197994007107</steamid><score>99476067</score><rank>66</rank><ugcid>867360315081561699</ugcid><details>0500000006000000</details></entry><entry><steamid>76561198087344093</steamid><score>99471753</score><rank>67</rank><ugcid>856103815151545107</ugcid><details>0500000006000000</details></entry><entry><steamid>76561198116399814</steamid><score>99471114</score><rank>68</rank><ugcid>862858215783461641</ugcid><details>0500000006000000</details></entry><entry><steamid>76561198157379218</steamid><score>99467512</score><rank>69</rank><ugcid>856102417388478725</ugcid><details>0500000006000000</details></entry><entry><steamid>76561198116714708</steamid><score>99467281</score><rank>70</rank><ugcid>872999668021762498</ugcid><details>0500000006000000</details></entry><entry><steamid>76561198014811697</steamid><score>99465746</score><rank>71</rank><ugcid>854977642895059744</ugcid><details>0500000006000000</details></entry><entry><steamid>76561198010696153</steamid><score>99465237</score><rank>72</rank><ugcid>854976916424790971</ugcid><details>0500000006000000</details></entry><entry><steamid>76561198281801546</steamid><score>99461438</score><rank>73</rank><ugcid>872992670373364385</ugcid><details>0500000006000000</details></entry><entry><steamid>76561198055100322</steamid><score>99458863</score><rank>74</rank><ugcid>865114802562557218</ugcid><details>0500000006000000</details></entry><entry><steamid>76561198097522980</steamid><score>99455941</score><rank>75</rank><ugcid>843715352048074650</ugcid><details>0500000006000000</details></entry><entry><steamid>76561198127768150</steamid><score>99441866</score><rank>76</rank><ugcid>869618433870176290</ugcid><details>0500000006000000</details></entry><entry><steamid>76561198040793421</steamid><score>99440383</score><rank>77</rank><ugcid>902267248839475678</ugcid><details>0500000006000000</details></entry><entry><steamid>76561198331593121</steamid><score>99439936</score><rank>78</rank><ugcid>866237183389916847</ugcid><details>0500000006000000</details></entry><entry><steamid>76561198049600266</steamid><score>99431034</score><rank>79</rank><ugcid>867368700915923089</ugcid><details>0500000006000000</details></entry><entry><steamid>76561198077327070</steamid><score>99428648</score><rank>80</rank><ugcid>877501262328723295</ugcid><details>0500000006000000</details></entry><entry><steamid>76561197997913064</steamid><score>99428037</score><rank>81</rank><ugcid>842588935651391676</ugcid><details>0500000006000000</details></entry><entry><steamid>76561198311172601</steamid><score>99422237</score><rank>82</rank><ugcid>853850382736265777</ugcid><details>0500000006000000</details></entry><entry><steamid>76561198322985690</steamid><score>99418608</score><rank>83</rank><ugcid>860606395589095366</ugcid><details>0500000006000000</details></entry><entry><steamid>76561198074408642</steamid><score>99418347</score><rank>84</rank><ugcid>860604658687258744</ugcid><details>0500000006000000</details></entry><entry><steamid>76561198248124092</steamid><score>99417471</score><rank>85</rank><ugcid>858356195372955357</ugcid><details>0500000006000000</details></entry><entry><steamid>76561198041535126</steamid><score>99414841</score><rank>86</rank><ugcid>848217154845420410</ugcid><details>0500000006000000</details></entry><entry><steamid>76561197998028449</steamid><score>99414226</score><rank>87</rank><ugcid>880874516076072216</ugcid><details>0500000006000000</details></entry><entry><steamid>76561198040558429</steamid><score>99412650</score><rank>88</rank><ugcid>850472868086869462</ugcid><details>0500000006000000</details></entry><entry><steamid>76561197963376009</steamid><score>99411206</score><rank>89</rank><ugcid>849345845410849976</ugcid><details>0500000006000000</details></entry><entry><steamid>76561198055473987</steamid><score>99405763</score><rank>90</rank><ugcid>880880230900947484</ugcid><details>0500000006000000</details></entry><entry><steamid>76561198112858645</steamid><score>99394347</score><rank>91</rank><ugcid>858360963913293127</ugcid><details>0500000006000000</details></entry><entry><steamid>76561198043074739</steamid><score>99390204</score><rank>92</rank><ugcid>865107062083190835</ugcid><details>0500000006000000</details></entry><entry><steamid>76561198369609157</steamid><score>99389278</score><rank>93</rank><ugcid>851599216707213797</ugcid><details>0500000006000000</details></entry><entry><steamid>76561198049426680</steamid><score>99387162</score><rank>94</rank><ugcid>848221615729948657</ugcid><details>0500000006000000</details></entry><entry><steamid>76561198017283351</steamid><score>99386786</score><rank>95</rank><ugcid>869615517002093128</ugcid><details>0500000006000000</details></entry><entry><steamid>76561197993615914</steamid><score>99380826</score><rank>96</rank><ugcid>856099859404636544</ugcid><details>0500000006000000</details></entry><entry><steamid>76561198150761378</steamid><score>99376947</score><rank>97</rank><ugcid>870744589428088670</ugcid><details>0500000006000000</details></entry><entry><steamid>76561198010188255</steamid><score>99374981</score><rank>98</rank><ugcid>863983329150728443</ugcid><details>0500000006000000</details></entry><entry><steamid>76561198013711696</steamid><score>99366415</score><rank>99</rank><ugcid>844843374874162590</ugcid><details>0500000006000000</details></entry><entry><steamid>76561197983354755</steamid><score>99366042</score><rank>100</rank><ugcid>879748394078961621</ugcid><details>0500000006000000</details></entry><entry><steamid>76561198055354778</steamid><score>99363821</score><rank>101</rank><ugcid>860604658687934908</ugcid><details>0500000006000000</details></entry><entry><steamid>76561198117749599</steamid><score>99362869</score><rank>102</rank><ugcid>868486534716832915</ugcid><details>0500000006000000</details></entry><entry><steamid>76561198077884640</steamid><score>99360696</score><rank>103</rank><ugcid>842591383658054930</ugcid><details>0500000006000000</details></entry><entry><steamid>76561198045129221</steamid><score>99354938</score><rank>104</rank><ugcid>876375362410140415</ugcid><details>0500000006000000</details></entry><entry><steamid>76561198162710298</steamid><score>99349171</score><rank>105</rank><ugcid>865113912180593284</ugcid><details>0500000006000000</details></entry><entry><steamid>76561198005597847</steamid><score>99348016</score><rank>106</rank><ugcid>861737125489599952</ugcid><details>0500000006000000</details></entry><entry><steamid>76561198189625178</steamid><score>99345178</score><rank>107</rank><ugcid>18446744073709551615</ugcid><details>0500000006000000</details></entry><entry><steamid>76561198095129892</steamid><score>99341626</score><rank>108</rank><ugcid>860613301493797702</ugcid><details>0500000006000000</details></entry><entry><steamid>76561198253734101</steamid><score>99336813</score><rank>109</rank><ugcid>885378430905125111</ugcid><details>0500000006000000</details></entry><entry><steamid>76561198006653420</steamid><score>99334088</score><rank>110</rank><ugcid>896637749305302968</ugcid><details>0500000006000000</details></entry><entry><steamid>76561198045159400</steamid><score>99333765</score><rank>111</rank><ugcid>859485831313376287</ugcid><details>0500000006000000</details></entry><entry><steamid>76561198097897774</steamid><score>99332616</score><rank>112</rank><ugcid>877497130881419382</ugcid><details>0500000006000000</details></entry><entry><steamid>76561198247671686</steamid><score>99329970</score><rank>113</rank><ugcid>860610777677217584</ugcid><details>0500000006000000</details></entry><entry><steamid>76561198056430350</steamid><score>99320890</score><rank>114</rank><ugcid>858355151797515228</ugcid><details>0500000006000000</details></entry><entry><steamid>76561198073897568</steamid><score>99320316</score><rank>115</rank><ugcid>854978700793535170</ugcid><details>0500000006000000</details></entry><entry><steamid>76561198045959196</steamid><score>99314290</score><rank>116</rank><ugcid>863991852094771976</ugcid><details>0500000006000000</details></entry><entry><steamid>76561198042997179</steamid><score>99309922</score><rank>117</rank><ugcid>867359862995505954</ugcid><details>0500000006000000</details></entry><entry><steamid>76561198204080252</steamid><score>99306496</score><rank>118</rank><ugcid>832455393924920960</ugcid><details>0500000006000000</details></entry><entry><steamid>76561198052787418</steamid><score>99304975</score><rank>119</rank><ugcid>870747131743806220</ugcid><details>0500000006000000</details></entry><entry><steamid>76561198043507340</steamid><score>99285550</score><rank>120</rank><ugcid>875245433940027320</ugcid><details>0500000006000000</details></entry><entry><steamid>76561197990353168</steamid><score>99282591</score><rank>121</rank><ugcid>18446744073709551615</ugcid><details>0500000006000000</details></entry><entry><steamid>76561198182599678</steamid><score>99281814</score><rank>122</rank><ugcid>859480077942611941</ugcid><details>0500000006000000</details></entry><entry><steamid>76561198053336843</steamid><score>99276870</score><rank>123</rank><ugcid>857233492663411412</ugcid><details>0500000006000000</details></entry><entry><steamid>76561198119131886</steamid><score>99276663</score><rank>124</rank><ugcid>857225761276722804</ugcid><details>0500000006000000</details></entry><entry><steamid>76561198019582667</steamid><score>99274912</score><rank>125</rank><ugcid>863984749720526842</ugcid><details>0500000006000000</details></entry><entry><steamid>76561198349048809</steamid><score>99273569</score><rank>126</rank><ugcid>860614032581233899</ugcid><details>0500000006000000</details></entry><entry><steamid>76561198264891429</steamid><score>99271040</score><rank>127</rank><ugcid>868492508838256761</ugcid><details>0500000006000000</details></entry><entry><steamid>76561198191856457</steamid><score>99262717</score><rank>128</rank><ugcid>880874516081025529</ugcid><details>0500000006000000</details></entry><entry><steamid>76561198040679848</steamid><score>99258763</score><rank>129</rank><ugcid>869617346484357532</ugcid><details>0500000006000000</details></entry><entry><steamid>76561197999948240</steamid><score>99245550</score><rank>130</rank><ugcid>850478605124882989</ugcid><details>0500000006000000</details></entry><entry><steamid>76561198041299005</steamid><score>99244621</score><rank>131</rank><ugcid>876371199060484606</ugcid><details>0500000006000000</details></entry><entry><steamid>76561198134879960</steamid><score>99226679</score><rank>132</rank><ugcid>860610103266076692</ugcid><details>0500000006000000</details></entry><entry><steamid>76561197994639744</steamid><score>99213107</score><rank>133</rank><ugcid>848222085756239875</ugcid><details>0500000006000000</details></entry><entry><steamid>76561198047951443</steamid><score>99202165</score><rank>134</rank><ugcid>865109554280508928</ugcid><details>0500000006000000</details></entry><entry><steamid>76561198061454277</steamid><score>99186981</score><rank>135</rank><ugcid>868491611904572382</ugcid><details>0500000006000000</details></entry><entry><steamid>76561198105525804</steamid><score>99173888</score><rank>136</rank><ugcid>18446744073709551615</ugcid><details>0500000006000000</details></entry><entry><steamid>76561198030445403</steamid><score>99170613</score><rank>137</rank><ugcid>863985014573100393</ugcid><details>0500000006000000</details></entry><entry><steamid>76561198043647383</steamid><score>99158200</score><rank>138</rank><ugcid>870744036727189864</ugcid><details>0500000006000000</details></entry><entry><steamid>76561198276360516</steamid><score>99154667</score><rank>139</rank><ugcid>860613625026174389</ugcid><details>0500000006000000</details></entry><entry><steamid>76561198287671933</steamid><score>99146307</score><rank>140</rank><ugcid>862860051670744350</ugcid><details>0500000006000000</details></entry><entry><steamid>76561198140748975</steamid><score>99135026</score><rank>141</rank><ugcid>861737125486097490</ugcid><details>0500000006000000</details></entry><entry><steamid>76561198132032035</steamid><score>99133346</score><rank>142</rank><ugcid>851595589203054980</ugcid><details>0500000006000000</details></entry><entry><steamid>76561198398161821</steamid><score>99131355</score><rank>143</rank><ugcid>870746586773526504</ugcid><details>0500000006000000</details></entry><entry><steamid>76561198076574469</steamid><score>99128778</score><rank>144</rank><ugcid>852723937094191878</ugcid><details>0500000006000000</details></entry><entry><steamid>76561198066799381</steamid><score>99127518</score><rank>145</rank><ugcid>836958517718447405</ugcid><details>0500000006000000</details></entry><entry><steamid>76561198000830156</steamid><score>99126552</score><rank>146</rank><ugcid>858356281481813504</ugcid><details>0500000006000000</details></entry><entry><steamid>76561198032791567</steamid><score>99121982</score><rank>147</rank><ugcid>868486767905356307</ugcid><details>0500000006000000</details></entry><entry><steamid>76561198078248081</steamid><score>99109931</score><rank>148</rank><ugcid>851597095575958129</ugcid><details>0500000006000000</details></entry><entry><steamid>76561198175432278</steamid><score>99105824</score><rank>149</rank><ugcid>861730335817907819</ugcid><details>0500000006000000</details></entry><entry><steamid>76561198005627330</steamid><score>99077912</score><rank>150</rank><ugcid>18446744073709551615</ugcid><details>0500000006000000</details></entry><entry><steamid>76561197980803449</steamid><score>99030732</score><rank>151</rank><ugcid>870743120056100841</ugcid><details>0500000006000000</details></entry><entry><steamid>76561198048992434</steamid><score>98998397</score><rank>152</rank><ugcid>854983602725429349</ugcid><details>0500000006000000</details></entry><entry><steamid>76561197963485955</steamid><score>98994324</score><rank>153</rank><ugcid>865112527943434623</ugcid><details>0500000006000000</details></entry><entry><steamid>76561198003517190</steamid><score>98985061</score><rank>154</rank><ugcid>866243532119644111</ugcid><details>0500000006000000</details></entry><entry><steamid>76561198120177142</steamid><score>98978828</score><rank>155</rank><ugcid>866241932578532093</ugcid><details>0500000006000000</details></entry><entry><steamid>76561197991890315</steamid><score>98911265</score><rank>156</rank><ugcid>862857039597903103</ugcid><details>0500000006000000</details></entry><entry><steamid>76561198025035257</steamid><score>98907240</score><rank>157</rank><ugcid>838084485063180372</ugcid><details>0500000006000000</details></entry><entry><steamid>76561198001827689</steamid><score>98871965</score><rank>158</rank><ugcid>851598802844883148</ugcid><details>0500000006000000</details></entry><entry><steamid>76561198097010083</steamid><score>98845160</score><rank>159</rank><ugcid>865108837549746939</ugcid><details>0500000006000000</details></entry><entry><steamid>76561197986014654</steamid><score>98832764</score><rank>160</rank><ugcid>861731380293444618</ugcid><details>0500000006000000</details></entry><entry><steamid>76561198044897664</steamid><score>98821428</score><rank>161</rank><ugcid>879748756622920128</ugcid><details>0500000006000000</details></entry><entry><steamid>76561198158193076</steamid><score>98813759</score><rank>162</rank><ugcid>848219424483447649</ugcid><details>0500000006000000</details></entry><entry><steamid>76561198119278666</steamid><score>98692663</score><rank>163</rank><ugcid>863986341962195220</ugcid><details>0500000006000000</details></entry><entry><steamid>76561198078206722</steamid><score>98675149</score><rank>164</rank><ugcid>856101548423804226</ugcid><details>0500000006000000</details></entry><entry><steamid>76561198055444056</steamid><score>98658158</score><rank>165</rank><ugcid>879748949104995889</ugcid><details>0500000006000000</details></entry><entry><steamid>76561198083676104</steamid><score>98617333</score><rank>166</rank><ugcid>843718112879738628</ugcid><details>0500000006000000</details></entry><entry><steamid>76561198060300596</steamid><score>98602531</score><rank>167</rank><ugcid>845967720022614514</ugcid><details>0500000006000000</details></entry><entry><steamid>76561198159222711</steamid><score>98593288</score><rank>168</rank><ugcid>863981955926030352</ugcid><details>0500000006000000</details></entry><entry><steamid>76561198120279679</steamid><score>98470386</score><rank>169</rank><ugcid>18446744073709551615</ugcid><details>0500000006000000</details></entry><entry><steamid>76561198116192989</steamid><score>98434523</score><rank>170</rank><ugcid>866239626959508163</ugcid><details>0500000006000000</details></entry><entry><steamid>76561198301440472</steamid><score>98425566</score><rank>171</rank><ugcid>862862324258826661</ugcid><details>0500000006000000</details></entry><entry><steamid>76561198058337534</steamid><score>98418950</score><rank>172</rank><ugcid>857228082462608497</ugcid><details>0500000006000000</details></entry><entry><steamid>76561198127282159</steamid><score>98305993</score><rank>173</rank><ugcid>876375256891271364</ugcid><details>0500000006000000</details></entry><entry><steamid>76561198388486745</steamid><score>98269722</score><rank>174</rank><ugcid>851598038666321709</ugcid><details>0500000006000000</details></entry><entry><steamid>76561198025184234</steamid><score>98257848</score><rank>175</rank><ugcid>880875784413133602</ugcid><details>0500000006000000</details></entry><entry><steamid>76561198008919371</steamid><score>98235194</score><rank>176</rank><ugcid>857233492655382069</ugcid><details>0500000006000000</details></entry><entry><steamid>76561197993241531</steamid><score>98204215</score><rank>177</rank><ugcid>867359279611300329</ugcid><details>0500000006000000</details></entry><entry><steamid>76561198264818312</steamid><score>98204075</score><rank>178</rank><ugcid>856110204444359045</ugcid><details>0500000006000000</details></entry><entry><steamid>76561198171801786</steamid><score>98162609</score><rank>179</rank><ugcid>858354407598431766</ugcid><details>0500000006000000</details></entry><entry><steamid>76561198023579762</steamid><score>98147854</score><rank>180</rank><ugcid>870744894165363950</ugcid><details>0500000006000000</details></entry><entry><steamid>76561198204592559</steamid><score>98139322</score><rank>181</rank><ugcid>876377264440531441</ugcid><details>0500000006000000</details></entry><entry><steamid>76561198042543022</steamid><score>98129922</score><rank>182</rank><ugcid>859480253189396934</ugcid><details>0500000006000000</details></entry><entry><steamid>76561198288324942</steamid><score>98069485</score><rank>183</rank><ugcid>886504300864115283</ugcid><details>0500000006000000</details></entry><entry><steamid>76561198037460198</steamid><score>98059164</score><rank>184</rank><ugcid>18446744073709551615</ugcid><details>0500000006000000</details></entry><entry><steamid>76561198149769495</steamid><score>98006082</score><rank>185</rank><ugcid>876370675544235306</ugcid><details>0500000006000000</details></entry><entry><steamid>76561198025119291</steamid><score>97945569</score><rank>186</rank><ugcid>871870489343073728</ugcid><details>0500000006000000</details></entry><entry><steamid>76561198078899114</steamid><score>97913070</score><rank>187</rank><ugcid>860606036730805637</ugcid><details>0500000006000000</details></entry><entry><steamid>76561198206120752</steamid><score>97908389</score><rank>188</rank><ugcid>844840646755905040</ugcid><details>0500000006000000</details></entry><entry><steamid>76561198041697587</steamid><score>97905467</score><rank>189</rank><ugcid>862856107320202223</ugcid><details>0500000006000000</details></entry><entry><steamid>76561198165199820</steamid><score>97895223</score><rank>190</rank><ugcid>875245159704510956</ugcid><details>0500000006000000</details></entry><entry><steamid>76561198407989937</steamid><score>97889227</score><rank>191</rank><ugcid>860611893418705766</ugcid><details>0500000006000000</details></entry><entry><steamid>76561198291153234</steamid><score>97884593</score><rank>192</rank><ugcid>18446744073709551615</ugcid><details>0500000006000000</details></entry><entry><steamid>76561198162268996</steamid><score>97867419</score><rank>193</rank><ugcid>883128131511897894</ugcid><details>0500000006000000</details></entry><entry><steamid>76561198120238675</steamid><score>97852526</score><rank>194</rank><ugcid>871873319170639660</ugcid><details>0500000006000000</details></entry><entry><steamid>76561198043939272</steamid><score>97850357</score><rank>195</rank><ugcid>847094232704770859</ugcid><details>0500000006000000</details></entry><entry><steamid>76561198026735379</steamid><score>97836248</score><rank>196</rank><ugcid>879748069808287446</ugcid><details>0500000006000000</details></entry><entry><steamid>76561198105899281</steamid><score>97793593</score><rank>197</rank><ugcid>853849707322123793</ugcid><details>0500000006000000</details></entry><entry><steamid>76561198026754370</steamid><score>97788517</score><rank>198</rank><ugcid>856101343595601711</ugcid><details>0500000006000000</details></entry><entry><steamid>76561198186652794</steamid><score>97782338</score><rank>199</rank><ugcid>858353649745613147</ugcid><details>0500000006000000</details></entry><entry><steamid>76561198170892994</steamid><score>97759012</score><rank>200</rank><ugcid>856106712927857383</ugcid><details>0500000006000000</details></entry><entry><steamid>76561198081255587</steamid><score>97754061</score><rank>201</rank><ugcid>859487850034957920</ugcid><details>0500000006000000</details></entry><entry><steamid>76561198141324733</steamid><score>97751173</score><rank>202</rank><ugcid>856108193880067683</ugcid><details>0500000006000000</details></entry><entry><steamid>76561198128729097</steamid><score>97744935</score><rank>203</rank><ugcid>850474042998047037</ugcid><details>0500000006000000</details></entry><entry><steamid>76561198031868643</steamid><score>97724780</score><rank>204</rank><ugcid>867358867351436938</ugcid><details>0500000006000000</details></entry><entry><steamid>76561198205461828</steamid><score>97702507</score><rank>205</rank><ugcid>830202752570263487</ugcid><details>0500000006000000</details></entry><entry><steamid>76561198018459017</steamid><score>97694978</score><rank>206</rank><ugcid>866242988959942350</ugcid><details>0500000006000000</details></entry><entry><steamid>76561198068575013</steamid><score>97637614</score><rank>207</rank><ugcid>854973983190995253</ugcid><details>0500000006000000</details></entry><entry><steamid>76561198268679215</steamid><score>97631115</score><rank>208</rank><ugcid>869613906108506611</ugcid><details>0500000006000000</details></entry><entry><steamid>76561198041371573</steamid><score>97600840</score><rank>209</rank><ugcid>859485277798885849</ugcid><details>0500000006000000</details></entry><entry><steamid>76561198354634744</steamid><score>97592756</score><rank>210</rank><ugcid>831329494970962053</ugcid><details>0500000006000000</details></entry><entry><steamid>76561198050270347</steamid><score>97538028</score><rank>211</rank><ugcid>871873664810991722</ugcid><details>0500000006000000</details></entry><entry><steamid>76561198045397869</steamid><score>97517013</score><rank>212</rank><ugcid>853851340196686920</ugcid><details>0500000006000000</details></entry><entry><steamid>76561198213973205</steamid><score>97483207</score><rank>213</rank><ugcid>856103154378561817</ugcid><details>0500000006000000</details></entry><entry><steamid>76561198272636519</steamid><score>97480317</score><rank>214</rank><ugcid>877498528033699550</ugcid><details>0500000006000000</details></entry><entry><steamid>76561198011723524</steamid><score>97465414</score><rank>215</rank><ugcid>876373664344563296</ugcid><details>0500000006000000</details></entry><entry><steamid>76561198330823995</steamid><score>97457644</score><rank>216</rank><ugcid>868488349347490259</ugcid><details>0500000006000000</details></entry><entry><steamid>76561198107763812</steamid><score>97434378</score><rank>217</rank><ugcid>832454898378693803</ugcid><details>0500000006000000</details></entry><entry><steamid>76561198031842824</steamid><score>96522255</score><rank>218</rank><ugcid>842590018017064213</ugcid><details>0500000006000000</details></entry></entries></response>