<?xml version="1.0" encoding="UTF-8" standalone="yes"?><response><appID>247080</appID><appFriendlyName>247080</appFriendlyName><leaderboardID>2048147</leaderboardID><totalLeaderboardEntries>201</totalLeaderboardEntries><entryStart>1</entryStart><entryEnd>201</entryEnd><resultCount>201</resultCount><entries><entry><steamid>76561198130335814</steamid><score>5343</score><rank>1</rank><ugcid>876372184775865896</ugcid><details>0100000006000000</details></entry><entry><steamid>76561198290656275</steamid><score>4777</score><rank>2</rank><ugcid>863986652008878599</ugcid><details>0100000006000000</details></entry><entry><steamid>76561198049600266</steamid><score>4678</score><rank>3</rank><ugcid>859480792482645459</ugcid><details>0100000006000000</details></entry><entry><steamid>76561198060290707</steamid><score>4313</score><rank>4</rank><ugcid>868495049280301803</ugcid><details>0100000006000000</details></entry><entry><steamid>76561198014098957</steamid><score>3824</score><rank>5</rank><ugcid>884252850325923172</ugcid><details>0100000006000000</details></entry><entry><steamid>76561198168248850</steamid><score>3706</score><rank>6</rank><ugcid>858352489483523934</ugcid><details>0100000006000000</details></entry><entry><steamid>76561198066896286</steamid><score>3678</score><rank>7</rank><ugcid>848217154846898032</ugcid><details>0400000005000000</details></entry><entry><steamid>76561198005627330</steamid><score>2884</score><rank>8</rank><ugcid>18446744073709551615</ugcid><details>0100000006000000</details></entry><entry><steamid>76561198052453103</steamid><score>1636</score><rank>9</rank><ugcid>866235466928722944</ugcid><details>0300000003000000</details></entry><entry><steamid>76561198058675540</steamid><score>1532</score><rank>10</rank><ugcid>860608011400829939</ugcid><details>0200000003000000</details></entry><entry><steamid>76561198141270473</steamid><score>1520</score><rank>11</rank><ugcid>863988638215228167</ugcid><details>0300000001000000</details></entry><entry><steamid>76561198025831717</steamid><score>1323</score><rank>12</rank><ugcid>858360963911852364</ugcid><details>0200000003000000</details></entry><entry><steamid>76561198255233637</steamid><score>1024</score><rank>13</rank><ugcid>852722580814697942</ugcid><details>0200000002000000</details></entry><entry><steamid>76561198137310107</steamid><score>917</score><rank>14</rank><ugcid>857232612840117659</ugcid><details>0200000002000000</details></entry><entry><steamid>76561198112122029</steamid><score>891</score><rank>15</rank><ugcid>856103543878318655</ugcid><details>0300000001000000</details></entry><entry><steamid>76561198230447556</steamid><score>765</score><rank>16</rank><ugcid>843717135677398893</ugcid><details>0200000001000000</details></entry><entry><steamid>76561197993247154</steamid><score>710</score><rank>17</rank><ugcid>858361973915751250</ugcid><details>0100000002000000</details></entry><entry><steamid>76561198257007655</steamid><score>699</score><rank>18</rank><ugcid>885384046195345433</ugcid><details>0200000001000000</details></entry><entry><steamid>76561197977891315</steamid><score>663</score><rank>19</rank><ugcid>851595589204863693</ugcid><details>0100000003000000</details></entry><entry><steamid>76561197996584729</steamid><score>648</score><rank>20</rank><ugcid>872995837445354561</ugcid><details>0100000003000000</details></entry><entry><steamid>76561198247671686</steamid><score>596</score><rank>21</rank><ugcid>869615233513979583</ugcid><details>0100000004000000</details></entry><entry><steamid>76561197975956199</steamid><score>537</score><rank>22</rank><ugcid>870744036727767637</ugcid><details>0200000001000000</details></entry><entry><steamid>76561198049022069</steamid><score>517</score><rank>23</rank><ugcid>877498811171159340</ugcid><details>0100000004000000</details></entry><entry><steamid>76561198079293395</steamid><score>488</score><rank>24</rank><ugcid>875244468225700442</ugcid><details>0100000003000000</details></entry><entry><steamid>76561198089956676</steamid><score>432</score><rank>25</rank><ugcid>845967473299917423</ugcid><details>0100000004000000</details></entry><entry><steamid>76561198142905184</steamid><score>425</score><rank>26</rank><ugcid>845970866272455065</ugcid><details>0100000002000000</details></entry><entry><steamid>76561198055814197</steamid><score>421</score><rank>27</rank><ugcid>861739709650710990</ugcid><details>0200000001000000</details></entry><entry><steamid>76561198060955065</steamid><score>398</score><rank>28</rank><ugcid>849346148987753974</ugcid><details>0100000002000000</details></entry><entry><steamid>76561198071684925</steamid><score>384</score><rank>29</rank><ugcid>839210690288362125</ugcid><details>0100000003000000</details></entry><entry><steamid>76561198155136197</steamid><score>338</score><rank>30</rank><ugcid>874123149302455396</ugcid><details>0100000001000000</details></entry><entry><steamid>76561198500347175</steamid><score>335</score><rank>31</rank><ugcid>878622169393293788</ugcid><details>0100000003000000</details></entry><entry><steamid>76561198006707816</steamid><score>333</score><rank>32</rank><ugcid>861734352041741660</ugcid><details>0100000003000000</details></entry><entry><steamid>76561198248086454</steamid><score>328</score><rank>33</rank><ugcid>868489617099058286</ugcid><details>0100000002000000</details></entry><entry><steamid>76561198031063446</steamid><score>319</score><rank>34</rank><ugcid>861729391590225732</ugcid><details>0100000002000000</details></entry><entry><steamid>76561198098373476</steamid><score>309</score><rank>35</rank><ugcid>863989535156568704</ugcid><details>0100000003000000</details></entry><entry><steamid>76561198076831862</steamid><score>286</score><rank>36</rank><ugcid>857226603475643720</ugcid><details>0100000002000000</details></entry><entry><steamid>76561198324266414</steamid><score>279</score><rank>37</rank><ugcid>860610936970201898</ugcid><details>0100000002000000</details></entry><entry><steamid>76561198020832630</steamid><score>272</score><rank>38</rank><ugcid>862858479873839721</ugcid><details>0100000004000000</details></entry><entry><steamid>76561198015886148</steamid><score>270</score><rank>39</rank><ugcid>845969603870713270</ugcid><details>0100000002000000</details></entry><entry><steamid>76561198024950122</steamid><score>267</score><rank>40</rank><ugcid>842587655440239220</ugcid><details>0000000003000000</details></entry><entry><steamid>76561198036664850</steamid><score>259</score><rank>41</rank><ugcid>894385949477476006</ugcid><details>0100000003000000</details></entry><entry><steamid>76561198262588625</steamid><score>246</score><rank>42</rank><ugcid>851596641409717655</ugcid><details>0100000002000000</details></entry><entry><steamid>76561198055686121</steamid><score>242</score><rank>43</rank><ugcid>853848638852655997</ugcid><details>0100000002000000</details></entry><entry><steamid>76561198230271884</steamid><score>231</score><rank>44</rank><ugcid>832454553858047672</ugcid><details>0000000002000000</details></entry><entry><steamid>76561197996031112</steamid><score>220</score><rank>45</rank><ugcid>892134380308428051</ugcid><details>0100000002000000</details></entry><entry><steamid>76561198005224434</steamid><score>202</score><rank>46</rank><ugcid>865114802553918473</ugcid><details>0100000002000000</details></entry><entry><steamid>76561197991940374</steamid><score>201</score><rank>47</rank><ugcid>848217154846552609</ugcid><details>0000000002000000</details></entry><entry><steamid>76561198039252582</steamid><score>194</score><rank>48</rank><ugcid>861730156885119864</ugcid><details>0100000002000000</details></entry><entry><steamid>76561198101480527</steamid><score>189</score><rank>49</rank><ugcid>868485988860039811</ugcid><details>0100000001000000</details></entry><entry><steamid>76561198000723329</steamid><score>189</score><rank>50</rank><ugcid>870742959327491323</ugcid><details>0100000002000000</details></entry><entry><steamid>76561198076839771</steamid><score>184</score><rank>51</rank><ugcid>18446744073709551615</ugcid><details>0100000003000000</details></entry><entry><steamid>76561197968400814</steamid><score>183</score><rank>52</rank><ugcid>861730486526634221</ugcid><details>0100000002000000</details></entry><entry><steamid>76561198040210547</steamid><score>179</score><rank>53</rank><ugcid>862857039595108337</ugcid><details>0100000002000000</details></entry><entry><steamid>76561198330876853</steamid><score>177</score><rank>54</rank><ugcid>850471263219647495</ugcid><details>0100000001000000</details></entry><entry><steamid>76561198377313973</steamid><score>176</score><rank>55</rank><ugcid>850471072102184612</ugcid><details>0100000002000000</details></entry><entry><steamid>76561198247813950</steamid><score>176</score><rank>56</rank><ugcid>848217372547743405</ugcid><details>0000000002000000</details></entry><entry><steamid>76561198010626924</steamid><score>173</score><rank>57</rank><ugcid>863991852092859298</ugcid><details>0100000002000000</details></entry><entry><steamid>76561198252282818</steamid><score>169</score><rank>58</rank><ugcid>870745221666178855</ugcid><details>0100000001000000</details></entry><entry><steamid>76561197997175557</steamid><score>169</score><rank>59</rank><ugcid>867368163160251552</ugcid><details>0100000002000000</details></entry><entry><steamid>76561197991890315</steamid><score>163</score><rank>60</rank><ugcid>862856504897892199</ugcid><details>0100000002000000</details></entry><entry><steamid>76561198041299005</steamid><score>153</score><rank>61</rank><ugcid>868491611905462710</ugcid><details>0100000002000000</details></entry><entry><steamid>76561198262832025</steamid><score>152</score><rank>62</rank><ugcid>854981439920776565</ugcid><details>0100000002000000</details></entry><entry><steamid>76561198029746492</steamid><score>141</score><rank>63</rank><ugcid>18446744073709551615</ugcid><details>0100000002000000</details></entry><entry><steamid>76561198064746710</steamid><score>139</score><rank>64</rank><ugcid>857227780212849054</ugcid><details>0100000001000000</details></entry><entry><steamid>76561198055305904</steamid><score>139</score><rank>65</rank><ugcid>862862973954236136</ugcid><details>0100000001000000</details></entry><entry><steamid>76561198400191895</steamid><score>137</score><rank>66</rank><ugcid>879750926819426167</ugcid><details>0100000002000000</details></entry><entry><steamid>76561198128423072</steamid><score>128</score><rank>67</rank><ugcid>829077678104495833</ugcid><details>0100000002000000</details></entry><entry><steamid>76561198046301627</steamid><score>122</score><rank>68</rank><ugcid>849343054877601546</ugcid><details>0000000001000000</details></entry><entry><steamid>76561198000486577</steamid><score>117</score><rank>69</rank><ugcid>872995499549008546</ugcid><details>0100000001000000</details></entry><entry><steamid>76561198136926537</steamid><score>114</score><rank>70</rank><ugcid>850473316797158254</ugcid><details>0100000002000000</details></entry><entry><steamid>76561198343703932</steamid><score>113</score><rank>71</rank><ugcid>884252361612568651</ugcid><details>0100000001000000</details></entry><entry><steamid>76561198202066144</steamid><score>111</score><rank>72</rank><ugcid>844843469649572824</ugcid><details>0100000002000000</details></entry><entry><steamid>76561198080214352</steamid><score>110</score><rank>73</rank><ugcid>831329213372641687</ugcid><details>0000000001000000</details></entry><entry><steamid>76561198280790906</steamid><score>109</score><rank>74</rank><ugcid>847092187908417761</ugcid><details>0100000002000000</details></entry><entry><steamid>76561198067053444</steamid><score>107</score><rank>75</rank><ugcid>865113719710452357</ugcid><details>0100000001000000</details></entry><entry><steamid>76561198018877505</steamid><score>106</score><rank>76</rank><ugcid>838084485064653677</ugcid><details>0000000001000000</details></entry><entry><steamid>76561198014525041</steamid><score>98</score><rank>77</rank><ugcid>854977642907245923</ugcid><details>0100000001000000</details></entry><entry><steamid>76561198041502590</steamid><score>96</score><rank>78</rank><ugcid>843713887519494391</ugcid><details>0000000001000000</details></entry><entry><steamid>76561198038497243</steamid><score>96</score><rank>79</rank><ugcid>866239812079505760</ugcid><details>0100000002000000</details></entry><entry><steamid>76561198028006207</steamid><score>91</score><rank>80</rank><ugcid>868485358663728922</ugcid><details>0100000001000000</details></entry><entry><steamid>76561198114364750</steamid><score>89</score><rank>81</rank><ugcid>860607050009067962</ugcid><details>0100000001000000</details></entry><entry><steamid>76561198346373173</steamid><score>88</score><rank>82</rank><ugcid>856108193886489262</ugcid><details>0100000001000000</details></entry><entry><steamid>76561198105899281</steamid><score>85</score><rank>83</rank><ugcid>840336028297410416</ugcid><details>0000000001000000</details></entry><entry><steamid>76561198118650689</steamid><score>81</score><rank>84</rank><ugcid>851596865083229612</ugcid><details>0100000001000000</details></entry><entry><steamid>76561198163522637</steamid><score>75</score><rank>85</rank><ugcid>884253484118681897</ugcid><details>0100000001000000</details></entry><entry><steamid>76561198004333418</steamid><score>75</score><rank>86</rank><ugcid>860603645841710144</ugcid><details>0100000001000000</details></entry><entry><steamid>76561198083548506</steamid><score>74</score><rank>87</rank><ugcid>844839873134915794</ugcid><details>0000000001000000</details></entry><entry><steamid>76561198067674748</steamid><score>74</score><rank>88</rank><ugcid>876373771690261096</ugcid><details>0100000001000000</details></entry><entry><steamid>76561198225477076</steamid><score>73</score><rank>89</rank><ugcid>834707417963824641</ugcid><details>0100000001000000</details></entry><entry><steamid>76561198019570999</steamid><score>73</score><rank>90</rank><ugcid>868486127025053139</ugcid><details>0100000001000000</details></entry><entry><steamid>76561198152352111</steamid><score>72</score><rank>91</rank><ugcid>863981158172855444</ugcid><details>0100000001000000</details></entry><entry><steamid>76561198065613005</steamid><score>68</score><rank>92</rank><ugcid>883132562672635931</ugcid><details>0100000001000000</details></entry><entry><steamid>76561198135459291</steamid><score>67</score><rank>93</rank><ugcid>877501985721828375</ugcid><details>0100000002000000</details></entry><entry><steamid>76561197995381091</steamid><score>64</score><rank>94</rank><ugcid>862856715456801308</ugcid><details>0100000001000000</details></entry><entry><steamid>76561198030445403</steamid><score>62</score><rank>95</rank><ugcid>862866169552626432</ugcid><details>0100000001000000</details></entry><entry><steamid>76561198058242559</steamid><score>60</score><rank>96</rank><ugcid>854973111413506667</ugcid><details>0000000002000000</details></entry><entry><steamid>76561198163253353</steamid><score>58</score><rank>97</rank><ugcid>853848077983525916</ugcid><details>0100000001000000</details></entry><entry><steamid>76561198011500315</steamid><score>57</score><rank>98</rank><ugcid>851595589197631472</ugcid><details>0100000001000000</details></entry><entry><steamid>76561198041333660</steamid><score>55</score><rank>99</rank><ugcid>832455062429943185</ugcid><details>0000000001000000</details></entry><entry><steamid>76561198037694272</steamid><score>55</score><rank>100</rank><ugcid>857230492628205555</ugcid><details>0100000001000000</details></entry><entry><steamid>76561198024808791</steamid><score>54</score><rank>101</rank><ugcid>850469689366257134</ugcid><details>0100000001000000</details></entry><entry><steamid>76561198048951312</steamid><score>52</score><rank>102</rank><ugcid>879748949105236218</ugcid><details>0100000001000000</details></entry><entry><steamid>76561198010296301</steamid><score>52</score><rank>103</rank><ugcid>858360963907690654</ugcid><details>0100000001000000</details></entry><entry><steamid>76561198112131695</steamid><score>51</score><rank>104</rank><ugcid>866233720798540473</ugcid><details>0100000001000000</details></entry><entry><steamid>76561198043818097</steamid><score>51</score><rank>105</rank><ugcid>853847846011777540</ugcid><details>0100000001000000</details></entry><entry><steamid>76561198208404921</steamid><score>49</score><rank>106</rank><ugcid>849347241498164130</ugcid><details>0100000001000000</details></entry><entry><steamid>76561198121399825</steamid><score>49</score><rank>107</rank><ugcid>872995499549494416</ugcid><details>0100000001000000</details></entry><entry><steamid>76561198063503328</steamid><score>48</score><rank>108</rank><ugcid>833580547906943249</ugcid><details>0000000001000000</details></entry><entry><steamid>76561198055673769</steamid><score>47</score><rank>109</rank><ugcid>851604923243955701</ugcid><details>0100000001000000</details></entry><entry><steamid>76561198237924540</steamid><score>46</score><rank>110</rank><ugcid>860613817782369241</ugcid><details>0100000001000000</details></entry><entry><steamid>76561198261710632</steamid><score>45</score><rank>111</rank><ugcid>868495740294057640</ugcid><details>0100000001000000</details></entry><entry><steamid>76561198029675156</steamid><score>45</score><rank>112</rank><ugcid>845969268595932241</ugcid><details>0100000002000000</details></entry><entry><steamid>76561198141375888</steamid><score>42</score><rank>113</rank><ugcid>848221516988682710</ugcid><details>0100000001000000</details></entry><entry><steamid>76561198065298583</steamid><score>42</score><rank>114</rank><ugcid>876374088968326301</ugcid><details>0100000001000000</details></entry><entry><steamid>76561198015131078</steamid><score>42</score><rank>115</rank><ugcid>860610549954703292</ugcid><details>0100000001000000</details></entry><entry><steamid>76561198142716311</steamid><score>40</score><rank>116</rank><ugcid>878623010267434309</ugcid><details>0100000001000000</details></entry><entry><steamid>76561197995754698</steamid><score>40</score><rank>117</rank><ugcid>842587834892592638</ugcid><details>0000000001000000</details></entry><entry><steamid>76561198135279969</steamid><score>39</score><rank>118</rank><ugcid>18446744073709551615</ugcid><details>0100000001000000</details></entry><entry><steamid>76561198093725114</steamid><score>39</score><rank>119</rank><ugcid>880875784415727667</ugcid><details>0100000001000000</details></entry><entry><steamid>76561198088894998</steamid><score>39</score><rank>120</rank><ugcid>862858215783886981</ugcid><details>0100000001000000</details></entry><entry><steamid>76561198153276353</steamid><score>38</score><rank>121</rank><ugcid>852725391210865116</ugcid><details>0100000001000000</details></entry><entry><steamid>76561198141240848</steamid><score>37</score><rank>122</rank><ugcid>850478605123802244</ugcid><details>0100000001000000</details></entry><entry><steamid>76561198078400604</steamid><score>37</score><rank>123</rank><ugcid>832454728736711137</ugcid><details>0000000001000000</details></entry><entry><steamid>76561198120371349</steamid><score>31</score><rank>124</rank><ugcid>852724482831594708</ugcid><details>0100000001000000</details></entry><entry><steamid>76561198082001020</steamid><score>30</score><rank>125</rank><ugcid>834706818234999027</ugcid><details>0000000001000000</details></entry><entry><steamid>76561198068014091</steamid><score>29</score><rank>126</rank><ugcid>849343611891484379</ugcid><details>0000000001000000</details></entry><entry><steamid>76561197997192319</steamid><score>28</score><rank>127</rank><ugcid>876374179346077794</ugcid><details>0100000001000000</details></entry><entry><steamid>76561197970698909</steamid><score>28</score><rank>128</rank><ugcid>897763649213988020</ugcid><details>0100000001000000</details></entry><entry><steamid>76561198069960098</steamid><score>23</score><rank>129</rank><ugcid>880876318125035042</ugcid><details>0100000001000000</details></entry><entry><steamid>76561198090283282</steamid><score>22</score><rank>130</rank><ugcid>856101166822499696</ugcid><details>0100000001000000</details></entry><entry><steamid>76561198022645970</steamid><score>22</score><rank>131</rank><ugcid>847091252323801978</ugcid><details>0000000001000000</details></entry><entry><steamid>76561198038045911</steamid><score>20</score><rank>132</rank><ugcid>854973288916402262</ugcid><details>0100000001000000</details></entry><entry><steamid>76561197999525256</steamid><score>20</score><rank>133</rank><ugcid>847094232706936465</ugcid><details>0100000001000000</details></entry><entry><steamid>76561197991897723</steamid><score>20</score><rank>134</rank><ugcid>868487995665769143</ugcid><details>0100000001000000</details></entry><entry><steamid>76561198044067609</steamid><score>19</score><rank>135</rank><ugcid>851605207743094946</ugcid><details>0100000001000000</details></entry><entry><steamid>76561198254590904</steamid><score>18</score><rank>136</rank><ugcid>859488684125421747</ugcid><details>0100000001000000</details></entry><entry><steamid>76561198073301045</steamid><score>18</score><rank>137</rank><ugcid>854976481397373100</ugcid><details>0100000001000000</details></entry><entry><steamid>76561198116453258</steamid><score>17</score><rank>138</rank><ugcid>861733332248991020</ugcid><details>0100000001000000</details></entry><entry><steamid>76561198372477030</steamid><score>16</score><rank>139</rank><ugcid>848217154856564811</ugcid><details>0000000001000000</details></entry><entry><steamid>76561198239473388</steamid><score>15</score><rank>140</rank><ugcid>18446744073709551615</ugcid><details>0100000001000000</details></entry><entry><steamid>76561197994995979</steamid><score>15</score><rank>141</rank><ugcid>880880864066270203</ugcid><details>0100000001000000</details></entry><entry><steamid>76561198250662326</steamid><score>13</score><rank>142</rank><ugcid>857227184336004402</ugcid><details>0100000001000000</details></entry><entry><steamid>76561198025213504</steamid><score>13</score><rank>143</rank><ugcid>18446744073709551615</ugcid><details>0100000001000000</details></entry><entry><steamid>76561198071101098</steamid><score>12</score><rank>144</rank><ugcid>863990816630313092</ugcid><details>0100000001000000</details></entry><entry><steamid>76561198042833671</steamid><score>12</score><rank>145</rank><ugcid>885384280494434530</ugcid><details>0100000001000000</details></entry><entry><steamid>76561198040935603</steamid><score>12</score><rank>146</rank><ugcid>877501800078832920</ugcid><details>0100000001000000</details></entry><entry><steamid>76561198017043146</steamid><score>12</score><rank>147</rank><ugcid>870744589432025792</ugcid><details>0100000001000000</details></entry><entry><steamid>76561198198164443</steamid><score>11</score><rank>148</rank><ugcid>866239812084746584</ugcid><details>0100000001000000</details></entry><entry><steamid>76561198110832703</steamid><score>11</score><rank>149</rank><ugcid>868486346351128604</ugcid><details>0100000001000000</details></entry><entry><steamid>76561197965780129</steamid><score>11</score><rank>150</rank><ugcid>840336028293137957</ugcid><details>0000000001000000</details></entry><entry><steamid>76561198031743447</steamid><score>10</score><rank>151</rank><ugcid>861736836879900984</ugcid><details>0100000001000000</details></entry><entry><steamid>76561198194962682</steamid><score>9</score><rank>152</rank><ugcid>870745729951256970</ugcid><details>0100000001000000</details></entry><entry><steamid>76561198043037245</steamid><score>9</score><rank>153</rank><ugcid>836958712908517696</ugcid><details>0000000001000000</details></entry><entry><steamid>76561198073233928</steamid><score>8</score><rank>154</rank><ugcid>845970674186129331</ugcid><details>0100000001000000</details></entry><entry><steamid>76561198040715709</steamid><score>8</score><rank>155</rank><ugcid>852724384000884147</ugcid><details>0100000001000000</details></entry><entry><steamid>76561198012595545</steamid><score>8</score><rank>156</rank><ugcid>854981112848536133</ugcid><details>0100000001000000</details></entry><entry><steamid>76561197995975034</steamid><score>8</score><rank>157</rank><ugcid>879754652779622849</ugcid><details>0100000001000000</details></entry><entry><steamid>76561198041055010</steamid><score>7</score><rank>158</rank><ugcid>856100901867384348</ugcid><details>0100000001000000</details></entry><entry><steamid>76561198027188884</steamid><score>7</score><rank>159</rank><ugcid>848220645317000792</ugcid><details>0100000001000000</details></entry><entry><steamid>76561198021622643</steamid><score>7</score><rank>160</rank><ugcid>862855045264735915</ugcid><details>0100000001000000</details></entry><entry><steamid>76561198312410277</steamid><score>6</score><rank>161</rank><ugcid>852722580815286096</ugcid><details>0100000001000000</details></entry><entry><steamid>76561198281069210</steamid><score>6</score><rank>162</rank><ugcid>880876094209698261</ugcid><details>0100000001000000</details></entry><entry><steamid>76561198260627986</steamid><score>6</score><rank>163</rank><ugcid>856099859401406124</ugcid><details>0100000001000000</details></entry><entry><steamid>76561198126715104</steamid><score>6</score><rank>164</rank><ugcid>833581302195589336</ugcid><details>0100000001000000</details></entry><entry><steamid>76561198189808102</steamid><score>5</score><rank>165</rank><ugcid>845965530652186549</ugcid><details>0000000001000000</details></entry><entry><steamid>76561198119843014</steamid><score>5</score><rank>166</rank><ugcid>868494332075828097</ugcid><details>0100000001000000</details></entry><entry><steamid>76561198343745626</steamid><score>4</score><rank>167</rank><ugcid>854983602723286301</ugcid><details>0100000001000000</details></entry><entry><steamid>76561198079259742</steamid><score>4</score><rank>168</rank><ugcid>861730486529227941</ugcid><details>0100000001000000</details></entry><entry><steamid>76561198392441088</steamid><score>3</score><rank>169</rank><ugcid>833580817773210751</ugcid><details>0000000001000000</details></entry><entry><steamid>76561198039464974</steamid><score>3</score><rank>170</rank><ugcid>875251016697762730</ugcid><details>0100000001000000</details></entry><entry><steamid>76561198025360933</steamid><score>3</score><rank>171</rank><ugcid>836958152010764911</ugcid><details>0000000001000000</details></entry><entry><steamid>76561198025317624</steamid><score>3</score><rank>172</rank><ugcid>874124286002504388</ugcid><details>0100000001000000</details></entry><entry><steamid>76561198011213152</steamid><score>3</score><rank>173</rank><ugcid>862863063073011218</ugcid><details>0100000001000000</details></entry><entry><steamid>76561198263453132</steamid><score>2</score><rank>174</rank><ugcid>18446744073709551615</ugcid><details>0100000001000000</details></entry><entry><steamid>76561198141405231</steamid><score>2</score><rank>175</rank><ugcid>850468950892720782</ugcid><details>0000000001000000</details></entry><entry><steamid>76561198131449841</steamid><score>2</score><rank>176</rank><ugcid>851597948809021308</ugcid><details>0100000001000000</details></entry><entry><steamid>76561198097438071</steamid><score>2</score><rank>177</rank><ugcid>863983651942556496</ugcid><details>0100000001000000</details></entry><entry><steamid>76561198005406964</steamid><score>2</score><rank>178</rank><ugcid>884252639598024564</ugcid><details>0100000001000000</details></entry><entry><steamid>76561197995199867</steamid><score>2</score><rank>179</rank><ugcid>849343453248204393</ugcid><details>0000000001000000</details></entry><entry><steamid>76561198124068711</steamid><score>1</score><rank>180</rank><ugcid>863991509458950709</ugcid><details>0100000001000000</details></entry><entry><steamid>76561197995001794</steamid><score>1</score><rank>181</rank><ugcid>862861700722813947</ugcid><details>0100000001000000</details></entry><entry><steamid>76561198310497560</steamid><score>0</score><rank>182</rank><ugcid>842589193402883157</ugcid><details>0100000001000000</details></entry><entry><steamid>76561198262618524</steamid><score>0</score><rank>183</rank><ugcid>854982302916143582</ugcid><details>0100000001000000</details></entry><entry><steamid>76561198168466680</steamid><score>0</score><rank>184</rank><ugcid>847093461250923912</ugcid><details>0100000001000000</details></entry><entry><steamid>76561198134879960</steamid><score>0</score><rank>185</rank><ugcid>843718003802692838</ugcid><details>0100000001000000</details></entry><entry><steamid>76561198132003445</steamid><score>0</score><rank>186</rank><ugcid>836958517716854729</ugcid><details>0000000001000000</details></entry><entry><steamid>76561198103094239</steamid><score>0</score><rank>187</rank><ugcid>876374509921717506</ugcid><details>0100000001000000</details></entry><entry><steamid>76561198090858568</steamid><score>0</score><rank>188</rank><ugcid>844841386258369520</ugcid><details>0100000001000000</details></entry><entry><steamid>76561198072681371</steamid><score>0</score><rank>189</rank><ugcid>849343239162627739</ugcid><details>0000000001000000</details></entry><entry><steamid>76561198071967556</steamid><score>0</score><rank>190</rank><ugcid>872997454952161371</ugcid><details>0100000001000000</details></entry><entry><steamid>76561198068134295</steamid><score>0</score><rank>191</rank><ugcid>869619962979925219</ugcid><details>0100000001000000</details></entry><entry><steamid>76561198067753700</steamid><score>0</score><rank>192</rank><ugcid>858356195371248129</ugcid><details>0100000001000000</details></entry><entry><steamid>76561198064374490</steamid><score>0</score><rank>193</rank><ugcid>842587834896680807</ugcid><details>0000000001000000</details></entry><entry><steamid>76561198062781434</steamid><score>0</score><rank>194</rank><ugcid>847091812074425742</ugcid><details>0000000001000000</details></entry><entry><steamid>76561198062515648</steamid><score>0</score><rank>195</rank><ugcid>865116901099331439</ugcid><details>0100000001000000</details></entry><entry><steamid>76561198056430350</steamid><score>0</score><rank>196</rank><ugcid>857228082454222313</ugcid><details>0100000001000000</details></entry><entry><steamid>76561198046243937</steamid><score>0</score><rank>197</rank><ugcid>851597253393650692</ugcid><details>0100000001000000</details></entry><entry><steamid>76561198024785468</steamid><score>0</score><rank>198</rank><ugcid>872999475013083710</ugcid><details>0100000001000000</details></entry><entry><steamid>76561198013332334</steamid><score>0</score><rank>199</rank><ugcid>868494332085119196</ugcid><details>0100000001000000</details></entry><entry><steamid>76561198011199437</steamid><score>0</score><rank>200</rank><ugcid>854974380624499708</ugcid><details>0100000001000000</details></entry><entry><steamid>76561197993289528</steamid><score>0</score><rank>201</rank><ugcid>833581013190940991</ugcid><details>0000000001000000</details></entry></entries></response>